odoo/addons/purchase_mto_owner/README.rst
odoo/addons/purchase_mto_owner/__init__.py
odoo/addons/purchase_mto_owner/__manifest__.py
odoo/addons/purchase_mto_owner/i18n/it.po
odoo/addons/purchase_mto_owner/i18n/purchase_mto_owner.pot
odoo/addons/purchase_mto_owner/models/__init__.py
odoo/addons/purchase_mto_owner/models/stock_rule.py
odoo/addons/purchase_mto_owner/readme/CONTRIBUTORS.md
odoo/addons/purchase_mto_owner/readme/DESCRIPTION.md
odoo/addons/purchase_mto_owner/static/description/icon.png
odoo/addons/purchase_mto_owner/static/description/index.html
odoo/addons/purchase_mto_owner/tests/__init__.py
odoo/addons/purchase_mto_owner/tests/test_purchase_mto_owner.py
odoo_addon_purchase_mto_owner-16.0.1.0.0.4.dist-info/METADATA
odoo_addon_purchase_mto_owner-16.0.1.0.0.4.dist-info/WHEEL
odoo_addon_purchase_mto_owner-16.0.1.0.0.4.dist-info/top_level.txt
odoo_addon_purchase_mto_owner-16.0.1.0.0.4.dist-info/RECORD
